Workbook
Name Slicer_Manager_Vlookup: #N/A
Name Slicer_Region: #N/A

Sheet Orders_Raw
A1: CustomerID | B1: ProductID | C1: Product Name | D1: Quantity | E1: Unit Price | F1: Order Date | G1: Delivery Date | H1: Region | I1: Status | J1: Sales Rep | K1: Notes
A2: CUST039 | B2: PRD027 | C2: BLENDER PRO | D2: 2 | E2: £31.65 | F2: 45230 | G2: 45233 | H2: east | I2: Returned | J2: TOM HUSSAIN | K2: Gift wrap
A3: CUST055 | B3: PRD024 | C3: RESISTANCE BANDS | D3: 3 | E3: $204.45 | F3: 45221 | G3: 45231 | H3: scotland | I3: Processing | J3: Nina Adams | K3: Fragile
A4: CUST053 | B4: PRD024 | C4: RESISTANCE BANDS | D4: 9 | E4: 30.51 | F4: 45308 | G4: 30.01.2024 | H4: WEST | I4: Pending | J4: Charlotte King | K4: Leave at door
A5: CUST049 | B5: PRD016 | C5: Stapler | D5: 7 | E5: 91.01 | F5: 24.03.2024 | G5: 29.03.2024 | H5: MIDLANDS | I5: Processing | J5: finn wilson | K5: Fragile
A6: CUST027 | B6: PRD040 | C6: Trainers Size 9 | D6: 3 | E6: $86.83 | F6: 45377 | G6: 45384 | H6: WEST | I6: Delivered | J6: george bell | K6: Express delivery
A7: CUST051 | B7: PRD017 | C7: RUNNING SHOES | D7: 7 | E7: £223.67 | F7: 45345 | G7: 45356 | H7: North | I7: Returned | J7: Finn Roberts
A8: CUST044 | B8: PRD011 | C8: Whiteboard A1 | D8: 9 | E8: 236.10 | F8: 45137 | G8: 45149 | H8: N.I. | I8: Pending | J8: Hannah Johnson | K8: Gift wrap
A9: CUST038 | B9: PRD003 | C9: USB-C HUB | D9: 1 | E9: £126.77 | F9: 45229 | G9: 45242 | H9: Wales | I9: Pending | J9: ryan foster
A10: CUST058 | B10: PRD029 | C10: french press | D10: 7 | E10: £127.18 | F10: 45295 | G10: 45299 | H10: Northern Ireland | I10: Pending | J10: Callum Singh
A11: CUST035 | B11: PRD016 | C11: Stapler | D11: 8 | E11: 158.37 | F11: 45264 | G11: 06.12.2023 | H11: NORTH | I11: Delivered | J11: Tara Scott | K11: Gift wrap
A12: CUST009 | B12: PRD038 | C12: Jeans 32X32 | D12: 1 | E12: 120.98 | F12: 17.12.2023 | G12: 45281 | H12: midlands | I12: Processing | J12: OLIVIA BAILEY | K12: Express delivery
A13: CUST032 | B13: PRD011 | C13: Whiteboard A1 | D13: 5 | E13: £84.81 | F13: 44999 | G13: 45003 | H13: EAST | I13: Returned | J13: PRIYA DAVIES
A14: CUST035 | B14: PRD006 | C14: WEBCAM HD | D14: 1 | E14: 228.47 | F14: 45097 | G14: 04.07.2023 | H14: EAST | I14: Delivered | J14: AMY WARD | K14: Gift wrap
A15: CUST048 | B15: PRD008 | C15: STANDING DESK | D15: 3 | E15: $150.47 | F15: 44939 | G15: 44946 | H15: West | I15: Returned | J15: PRIYA EVANS
A16: CUST017 | B16: PRD021 | C16: PROTEIN POWDER 1KG | D16: 10 | E16: 16.53 | F16: 44947 | G16: 44950 | H16: NORTH | I16: Returned | J16: Adam Baker
A17: CUST052 | B17: PRD005 | C17: MONITOR 27IN | D17: 1 | E17: $108.05 | F17: 45251 | G17: 02.12.2023 | H17: North | I17: Cancelled | J17: Jess Clarke
A18: CUST049 | B18: PRD019 | C18: Yoga Mat | D18: 7 | E18: £127.46 | F18: 45105 | G18: 45112 | H18: west | I18: Cancelled | J18: Ethan Singh | K18: Fragile
A19: CUST037 | B19: PRD002 | C19: Wireless Mouse | D19: 4 | E19: £42.12 | F19: 45234 | G19: 45239 | H19: wales | I19: Delivered | J19: Charlotte Williams | K19: Fragile
A20: CUST005 | B20: PRD011 | C20: Whiteboard A1 | D20: 10 | E20: 72.28 | F20: 16.05.2023 | G20: 45072 | H20: scotland | I20: Pending | J20: Luke Singh | K20: Express delivery
A21: CUST028 | B21: PRD040 | C21: Trainers Size 9 | D21: 4 | E21: £272.14 | F21: 45064 | G21: 45076 | H21: EAST | I21: Pending | J21: Charlotte Ahmed
A22: CUST016 | B22: PRD016 | C22: Stapler | D22: 9 | E22: 70.34 | F22: 45331 | G22: 18.02.2024 | H22: WEST | I22: Cancelled | J22: nadia singh
A23: CUST007 | B23: PRD002 | C23: Wireless Mouse | D23: 1 | E23: £132.71 | F23: 14.07.2023 | G23: 45132 | H23: EAST | I23: Cancelled | J23: James Singh | K23: Gift wrap
A24: CUST047 | B24: PRD024 | C24: RESISTANCE BANDS | D24: 2 | E24: 50.30 | F24: 45072 | G24: 45081 | H24: West | I24: Delivered | J24: SARAH BELL
A25: CUST054 | B25: PRD025 | C25: COFFEE MAKER | D25: 1 | E25: £109.56 | F25: 45311 | G25: 45320 | H25: South | I25: Delivered | J25: GRACE WALKER | K25: Leave at door
A26: CUST049 | B26: PRD005 | C26: MONITOR 27IN | D26: 1 | E26: 131.90 | F26: 45009 | G26: 45017 | H26: WALES | I26: Cancelled | J26: Fatima Bell | K26: Gift wrap
A27: CUST005 | B27: PRD003 | C27: USB-C HUB | D27: 4 | E27: $82.31 | F27: 45031 | G27: 45036 | H27: west | I27: Processing | J27: George Cox
A28: CUST005 | B28: PRD025 | C28: COFFEE MAKER | D28: 2 | E28: £222.09 | F28: 45433 | G28: 45440 | H28: West | I28: Cancelled | J28: Nina Walker | K28: Gift wrap
A29: CUST048 | B29: PRD032 | C29: Python for Beginners | D29: 6 | E29: 298.84 | F29: 44947 | G29: 44957 | H29: East | I29: Pending | J29: Lily Malik
A30: CUST008 | B30: PRD021 | C30: PROTEIN POWDER 1KG | D30: 4 | E30: 63.48 | F30: 44940 | G30: 44954 | H30: east | I30: Cancelled | J30: Grace Bailey | K30: Gift wrap
A31: CUST049 | B31: PRD027 | C31: BLENDER PRO | D31: 7 | E31: 190.64 | F31: 45202 | G31: 45207 | H31: EAST | I31: Delivered | J31: Mohammed Shah | K31: Gift wrap
A32: CUST026 | B32: PRD009 | C32: Desk Lamp | D32: 5 | E32: £180.52 | F32: 45440 | G32: 45454 | H32: MIDLANDS | I32: Pending | J32: RUBY BAKER | K32: Express delivery
A33: CUST033 | B33: PRD009 | C33: Desk Lamp | D33: 9 | E33: £71.29 | F33: 45455 | G33: 45459 | H33: wales | I33: Returned | J33: James Adams
A34: CUST028 | B34: PRD006 | C34: WEBCAM HD | D34: 7 | E34: 138.99 | F34: 44931 | G34: 19.01.2023 | H34: WEST | I34: Pending | J34: emma taylor | K34: Gift wrap
A35: CUST053 | B35: PRD036 | C35: Self Help Guide | D35: 4 | E35: 29.42 | F35: 45258 | G35: 45272 | H35: Mids | I35: Cancelled | J35: Owen Williams | K35: Gift wrap
A36: CUST035 | B36: PRD040 | C36: Trainers Size 9 | D36: 6 | E36: £67.80 | F36: 44971 | G36: 44983 | H36: west | I36: Returned | J36: Max Ward
A37: CUST036 | B37: PRD012 | C37: Notebook Pack | D37: 9 | E37: $253.94 | F37: 11.11.2023 | G37: 45242 | H37: scotland | I37: Pending | J37: Lily Williams
A38: CUST044 | B38: PRD036 | C38: Self Help Guide | D38: 5 | E38: £250.69 | F38: 45263 | G38: 15.12.2023 | H38: Midlands | I38: Cancelled | J38: LILY ROBERTS
A39: CUST041 | B39: PRD006 | C39: WEBCAM HD | D39: 8 | E39: $119.12 | F39: 45315 | G39: 45325 | H39: Midlands | I39: Pending | J39: NADIA BELL
A40: CUST044 | B40: PRD007 | C40: OFFICE CHAIR | D40: 1 | E40: £112.20 | F40: 45169 | G40: 45171 | H40: MIDLANDS | J40: DANIEL WILSON | K40: Gift wrap
A41: CUST036 | B41: PRD033 | C41: Data Science Handbook | D41: 9 | E41: £80.88 | F41: 45348 | G41: 45357 | H41: MIDLANDS | I41: Processing | J41: Hannah Murphy | K41: Leave at door
A42: CUST058 | B42: PRD032 | C42: Python for Beginners | D42: 4 | E42: 144.99 | F42: 26.05.2024 | G42: 45442 | H42: north | I42: Processing | J42: Liam Bell
A43: CUST050 | B43: PRD035 | C43: Cook Book 2024 | D43: 1 | E43: £22.19 | F43: 44942 | G43: 20.01.2023 | H43: Northern Ireland | I43: Delivered | J43: Mia Williams | K43: Express delivery
A44: CUST041 | B44: PRD028 | C44: Air Fryer | D44: 3 | E44: $266.77 | F44: 45395 | G44: 45409 | H44: North | I44: Cancelled | J44: OLIVIA WILLIAMS | K44: Fragile
A45: CUST049 | B45: PRD032 | C45: Python for Beginners | D45: 3 | E45: £87.41 | F45: 45080 | G45: 45093 | H45: scotland | I45: Processing | J45: AMELIA GREEN
A46: CUST031 | B46: PRD006 | C46: WEBCAM HD | D46: 7 | E46: £213.00 | F46: 45237 | G46: 45238 | H46: East | I46: Cancelled
A47: CUST020 | B47: PRD017 | C47: RUNNING SHOES | D47: 6 | E47: 119.84 | F47: 45092 | G47: 45098 | H47: north | I47: Returned | J47: ruby foster
A48: CUST047 | B48: PRD012 | C48: Notebook Pack | D48: 6 | E48: $171.33 | F48: 19.02.2023 | G48: 44983 | H48: East | I48: Pending | J48: Owen Davies | K48: Leave at door
A49: CUST035 | B49: PRD021 | C49: PROTEIN POWDER 1KG | D49: 6 | E49: 293.27 | F49: 45018 | G49: 13.04.2023 | H49: wales | I49: Pending | J49: FATIMA BAILEY | K49: Leave at door
A50: CUST012 | B50: PRD004 | C50: Mechanical Keyboard | D50: 1 | E50: 28.58 | F50: 24.01.2024 | G50: 45327 | H50: N.I. | I50: Returned | J50: James Thomas | K50: Fragile
A51: CUST021 | B51: PRD018 | C51: Gym Bag | D51: 3 | E51: £188.01 | F51: 45419 | G51: 45425 | H51: Northern Ireland | I51: Processing | J51: Grace Foster
A52: CUST035 | B52: PRD029 | C52: french press | D52: 10 | E52: 140.79 | F52: 45422 | G52: 45433 | H52: West | I52: Cancelled | J52: Maya Smith | K52: Fragile
A53: CUST054 | B53: PRD004 | C53: Mechanical Keyboard | D53: 4 | E53: 40.53 | F53: 45366 | G53: 28.03.2024 | H53: south | I53: Returned | J53: HANNAH ROBERTS | K53: Express delivery
A54: CUST002 | B54: PRD023 | C54: First Aid Kit | D54: 1 | E54: £287.57 | F54: 44966 | G54: 44970 | H54: west | I54: Returned | J54: AARON SMITH
A55: CUST031 | B55: PRD023 | C55: First Aid Kit | D55: 6 | E55: £105.98 | F55: 45176 | G55: 08.09.2023 | H55: south | I55: Returned | J55: Mohammed Walker | K55: Gift wrap
A56: CUST022 | B56: PRD012 | C56: Notebook Pack | D56: 8 | E56: £102.27 | F56: 45418 | G56: 45419 | H56: NORTH | I56: Returned | J56: max patel
A57: CUST028 | B57: PRD024 | C57: RESISTANCE BANDS | D57: 1 | E57: £54.94 | F57: 45301 | G57: 45307 | H57: SCOTLAND | I57: Processing | J57: ETHAN SHAH | K57: Gift wrap
A58: CUST006 | B58: PRD031 | C58: Novel - The Shift | D58: 2 | E58: £237.33 | F58: 45041 | G58: 02.05.2023 | H58: west | I58: Delivered | J58: daniel gupta
A59: CUST011 | B59: PRD001 | C59: Laptop Pro 15 | D59: 6 | E59: 96.36 | F59: 45202 | G59: 45214 | H59: East | I59: Delivered | J59: sophie williams | K59: Leave at door
A60: CUST010 | B60: PRD004 | C60: Mechanical Keyboard | D60: 3 | E60: £88.41 | F60: 45192 | G60: 29.09.2023 | H60: north | I60: Cancelled | J60: Lily Davies
A61: CUST001 | B61: PRD038 | C61: Jeans 32X32 | D61: 4 | E61: 97.06 | F61: 45295 | G61: 45305 | H61: West | I61: Returned | J61: Ruby Hall | K61: Express delivery
A62: CUST015 | B62: PRD019 | C62: Yoga Mat | D62: 9 | E62: £14.10 | F62: 45275 | G62: 45288 | H62: South | I62: Pending | J62: mohammed roberts | K62: Fragile
A63: CUST005 | B63: PRD006 | C63: WEBCAM HD | D63: 3 | E63: 7.66 | F63: 45053 | G63: 09.05.2023 | H63: NORTH | I63: Cancelled | J63: NADIA COOPER
A64: CUST039 | B64: PRD004 | C64: Mechanical Keyboard | D64: 7 | E64: £56.36 | F64: 45451 | G64: 14.06.2024 | H64: scotland | I64: Cancelled | J64: George King
A65: CUST043 | B65: PRD013 | C65: Ballpoint Pens X10 | D65: 1 | E65: £156.01 | F65: 30.08.2023 | G65: 45176 | H65: Mids | I65: Pending | J65: EMMA WILLIAMS
A66: CUST051 | B66: PRD012 | C66: Notebook Pack | D66: 4 | E66: 41.71 | F66: 45006 | G66: 45020 | H66: south | I66: Pending | J66: Ella Sharma
A67: CUST040 | B67: PRD018 | C67: Gym Bag | D67: 10 | E67: $291.62 | F67: 45378 | G67: 45387 | H67: Scot. | I67: Pending | J67: Owen Shah
A68: CUST056 | B68: PRD005 | C68: MONITOR 27IN | D68: 3 | E68: $181.87 | F68: 45055 | G68: 45065 | H68: Midlands | I68: Cancelled | J68: ben thomas
A69: CUST039 | B69: PRD013 | C69: Ballpoint Pens X10 | D69: 9 | E69: £224.76 | F69: 45062 | G69: 45073 | H69: Scot. | I69: Pending | J69: AMY COOPER | K69: Express delivery
A70: CUST018 | B70: PRD015 | C70: Printer Paper A4 | D70: 10 | E70: 153.61 | F70: 45421 | G70: 12.05.2024 | H70: MIDLANDS | I70: Processing | J70: Grace Walker | K70: Gift wrap
A71: CUST034 | B71: PRD030 | C71: Mug Set x4 | D71: 5 | E71: £8.22 | F71: 15.01.2023 | G71: 44954 | H71: Midlands | I71: Pending | J71: Ben Ali
A72: CUST013 | B72: PRD010 | C72: filing cabinet | D72: 1 | E72: 238.81 | F72: 45420 | G72: 45430 | H72: Mids | I72: Returned | J72: Ella Hussain
A73: CUST038 | B73: PRD038 | C73: Jeans 32X32 | D73: 10 | E73: £112.49 | F73: 45258 | G73: 45270 | H73: south | I73: Pending | J73: Fatima Baker | K73: Express delivery
A74: CUST037 | B74: PRD031 | C74: Novel - The Shift | D74: 1 | E74: 94.77 | F74: 18.04.2024 | G74: 45414 | H74: east | I74: Returned | J74: Priya Patel
A75: CUST045 | B75: PRD040 | C75: Trainers Size 9 | D75: 3 | E75: 65.15 | F75: 02.11.2023 | G75: 45234 | H75: Scot. | I75: Pending | J75: Jack Ali
A76: CUST016 | B76: PRD033 | C76: Data Science Handbook | D76: 5 | E76: $143.53 | F76: 45265 | G76: 45272 | H76: scotland | I76: Processing | J76: DANIEL CLARKE | K76: Fragile
A77: CUST031 | B77: PRD017 | C77: RUNNING SHOES | D77: 6 | E77: £209.22 | F77: 45004 | G77: 45013 | H77: West | I77: Returned | J77: Amelia Sharma
A78: CUST035 | B78: PRD004 | C78: Mechanical Keyboard | D78: 4 | E78: 280.99 | F78: 45347 | G78: 45348 | H78: West | I78: Pending | J78: FINN MURPHY
A79: CUST021 | B79: PRD025 | C79: COFFEE MAKER | D79: 6 | E79: $209.94 | F79: 45417 | G79: 45430 | H79: Wales | I79: Pending | J79: James Scott | K79: Leave at door
A80: CUST018 | B80: PRD024 | C80: RESISTANCE BANDS | D80: 2 | E80: £76.22 | F80: 45397 | G80: 45407 | H80: East | I80: Delivered | J80: Tara Ali
A81: CUST033 | B81: PRD019 | C81: Yoga Mat | D81: 8 | E81: 13.73 | F81: 45410 | G81: 45413 | H81: WALES | I81: Delivered | J81: Lucas Hall
A82: CUST003 | B82: PRD013 | C82: Ballpoint Pens X10 | D82: 10 | E82: 261.58 | F82: 45469 | G82: 45473 | H82: N.I. | I82: Delivered | J82: Callum Ali
A83: CUST004 | B83: PRD034 | C83: business strategy | D83: 3 | E83: £119.54 | F83: 45187 | G83: 45198 | H83: NORTH | I83: Cancelled | J83: ALI MORRIS | K83: Fragile
A84: CUST037 | B84: PRD020 | C84: Water Bottle | D84: 2 | E84: 156.29 | F84: 45305 | G84: 45316 | H84: Scotland | I84: Delivered | J84: Ravi Wilson
A85: CUST022 | B85: PRD034 | C85: business strategy | D85: 7 | E85: 235.41 | F85: 45307 | G85: 45320 | H85: scotland | I85: Returned | J85: Sophie Khan
A86: CUST026 | B86: PRD003 | C86: USB-C HUB | D86: 6 | E86: £207.24 | F86: 45190 | G86: 45202 | H86: West | I86: Cancelled | J86: Noah Sharma | K86: Fragile
A87: CUST020 | B87: PRD033 | C87: Data Science Handbook | D87: 2 | E87: 271.31 | F87: 17.08.2023 | G87: 45167 | H87: Scotland | I87: Cancelled | J87: Owen Green
A88: CUST057 | B88: PRD038 | C88: Jeans 32X32 | D88: 8 | E88: £208.51 | F88: 45202 | G88: 45216 | H88: north | I88: Returned | J88: MOHAMMED JONES | K88: Leave at door
A89: CUST034 | B89: PRD014 | C89: Sticky Notes | D89: 10 | E89: 192.27 | F89: 45383 | G89: 45387 | H89: SCOTLAND | I89: Processing | J89: Emma Smith
A90: CUST026 | B90: PRD017 | C90: RUNNING SHOES | D90: 4 | E90: 92.11 | F90: 45059 | G90: 14.05.2023 | H90: SCOTLAND | I90: Returned | J90: LUCAS THOMAS | K90: Fragile
A91: CUST014 | B91: PRD004 | C91: Mechanical Keyboard | D91: 10 | E91: 16.71 | F91: 45259 | G91: 45266 | H91: MIDLANDS | I91: Pending | J91: Finn Clarke | K91: Express delivery
A92: CUST058 | B92: PRD015 | C92: Printer Paper A4 | D92: 2 | E92: 102.95 | F92: 44928 | G92: 44930 | H92: North | I92: Pending | J92: Jack Sharma
A93: CUST023 | B93: PRD029 | C93: french press | D93: 10 | E93: £124.09 | F93: 45339 | G93: 45347 | H93: Wales | I93: Cancelled | J93: Ali Hussain
A94: CUST047 | B94: PRD032 | C94: Python for Beginners | D94: 9 | E94: £44.31 | F94: 45355 | G94: 12.03.2024 | H94: MIDLANDS | I94: Cancelled | J94: ali roberts
A95: CUST007 | B95: PRD020 | C95: Water Bottle | D95: 1 | E95: 90.83 | F95: 18.07.2023 | G95: 45139 | H95: wales | I95: Processing | J95: Noah Foster
A96: CUST004 | B96: PRD002 | C96: Wireless Mouse | D96: 9 | E96: $149.61 | F96: 11.08.2023 | G96: 45151 | H96: Scot. | I96: Returned | J96: jack malik | K96: Express delivery
A97: CUST045 | B97: PRD022 | C97: vitamin d 90tabs | D97: 10 | E97: 247.79 | F97: 45026 | G97: 45034 | H97: west | I97: Delivered | J97: Sophie Gupta
A98: CUST046 | B98: PRD023 | C98: First Aid Kit | D98: 3 | E98: 90.9 | F98: 45302 | G98: 45307 | H98: south | I98: Returned | J98: Freya Baker | K98: Express delivery
A99: CUST019 | B99: PRD025 | C99: COFFEE MAKER | D99: 5 | E99: 265.84 | F99: 45340 | G99: 45346 | H99: North | I99: Returned | J99: NOAH BELL
A100: CUST030 | B100: PRD023 | C100: First Aid Kit | D100: 2 | E100: 121.54 | F100: 45411 | G100: 45417 | H100: wales | I100: Returned | J100: Callum Green
...

Sheet Orders_Clean
A1: CustomerID | B1: ProductID | C1: Product Name | D1: Quantity | E1: Unit Price | F1: Order Date | G1: Delivery Date | H1: Region | I1: Status | J1: Sales Rep | K1: Notes | M1: Formulas | N1: Total Revenue Per Purchase | O1: Delivery Speed 1 | P1: Delivery Speed 2 | Q1: Order Date Month | R1: Order Date Year | S1: Order Date Concatenate | T1: Category | V1: February Sales Target | W1: February
A2: CUST001 | B2: PRD038 | C2: Jeans 32X32 | D2: 4 | E2: 97.06 | F2: 45295 | G2: 45305 | H2: West England | I2: Returned | J2: Ruby Hall | K2: Express delivery | N2: =PRODUCT(D2:E2) -> 388.24 | O2: =_xlfn.DAYS(G2,F2) -> 10 | P2: {=_xlfn.IFS(O2<4,"Speedy",O2<7,"Standard",O2>=7,"Slow")} -> Slow | Q2: =TEXT(F2,"mmmm") -> January | R2: =TEXT(F2,"yyyy") -> 2024 | S2: =CONCATENATE(Q2," ",R2) -> January 2024 | T2: =_xlfn.XLOOKUP(B2,REF_Products!$A$2:$A$41,REF_Products!$C$2:$C$41) -> Clothing | V2: North England | W2: =_xlfn.XLOOKUP(REF_Regions!$K$1,REF_Regions!$I$1:$U$1,REF_Regions!I2:U2) -> 72740
A3: CUST002 | B3: PRD017 | C3: Running Shoes | D3: 1 | E3: 299.62 | F3: 45330 | G3: 45331 | H3: South England | I3: Pending | J3: Ravi Clarke | K3: Blank | N3: =PRODUCT(D3:E3) -> 299.62 | O3: =_xlfn.DAYS(G3,F3) -> 1 | P3: {=_xlfn.IFS(O3<4,"Speedy",O3<7,"Standard",O3>=7,"Slow")} -> Speedy | Q3: =TEXT(F3,"mmmm") -> February | R3: =TEXT(F3,"yyyy") -> 2024 | S3: =CONCATENATE(Q3," ",R3) -> February 2024 | T3: =_xlfn.XLOOKUP(B3,REF_Products!$A$2:$A$41,REF_Products!$C$2:$C$41) -> Sportswear | V3: South England | W3: =_xlfn.XLOOKUP(REF_Regions!$K$1,REF_Regions!$I$1:$U$1,REF_Regions!I3:U3) -> 88927
A4: CUST003 | B4: PRD023 | C4: First Aid Kit | D4: 1 | E4: 287.57 | F4: 44966 | G4: 44970 | H4: West England | I4: Returned | J4: Aaron Smith | K4: Blank | N4: =PRODUCT(D4:E4) -> 287.57 | O4: =_xlfn.DAYS(G4,F4) -> 4 | P4: {=_xlfn.IFS(O4<4,"Speedy",O4<7,"Standard",O4>=7,"Slow")} -> Standard | Q4: =TEXT(F4,"mmmm") -> February | R4: =TEXT(F4,"yyyy") -> 2023 | S4: =CONCATENATE(Q4," ",R4) -> February 2023 | T4: =_xlfn.XLOOKUP(B4,REF_Products!$A$2:$A$41,REF_Products!$C$2:$C$41) -> Health | V4: East England | W4: =_xlfn.XLOOKUP(REF_Regions!$K$1,REF_Regions!$I$1:$U$1,REF_Regions!I4:U4) -> 107670
A5: CUST004 | B5: PRD035 | C5: Cook Book 2024 | D5: 2 | E5: 104.67 | F5: 44952 | G5: 44954 | H5: South England | I5: Processing | J5: Noah Hussain | K5: Express delivery | N5: =PRODUCT(D5:E5) -> 209.34 | O5: =_xlfn.DAYS(G5,F5) -> 2 | P5: {=_xlfn.IFS(O5<4,"Speedy",O5<7,"Standard",O5>=7,"Slow")} -> Speedy | Q5: =TEXT(F5,"mmmm") -> January | R5: =TEXT(F5,"yyyy") -> 2023 | S5: =CONCATENATE(Q5," ",R5) -> January 2023 | T5: =_xlfn.XLOOKUP(B5,REF_Products!$A$2:$A$41,REF_Products!$C$2:$C$41) -> Books | V5: West England | W5: =_xlfn.XLOOKUP(REF_Regions!$K$1,REF_Regions!$I$1:$U$1,REF_Regions!I5:U5) -> 113395
A6: CUST005 | B6: PRD013 | C6: Ballpoint Pens X10 | D6: 10 | E6: 261.58 | F6: 45469 | G6: 45473 | H6: Northern Ireland | I6: Delivered | J6: Callum Ali | K6: Blank | N6: =PRODUCT(D6:E6) -> 2615.8 | O6: =_xlfn.DAYS(G6,F6) -> 4 | P6: {=_xlfn.IFS(O6<4,"Speedy",O6<7,"Standard",O6>=7,"Slow")} -> Standard | Q6: =TEXT(F6,"mmmm") -> June | R6: =TEXT(F6,"yyyy") -> 2024 | S6: =CONCATENATE(Q6," ",R6) -> June 2024 | T6: =_xlfn.XLOOKUP(B6,REF_Products!$A$2:$A$41,REF_Products!$C$2:$C$41) -> Stationery | V6: Midlands | W6: =_xlfn.XLOOKUP(REF_Regions!$K$1,REF_Regions!$I$1:$U$1,REF_Regions!I6:U6) -> 112160
A7: CUST006 | B7: PRD022 | C7: Vitamin D 90Tabs | D7: 5 | E7: 69.37 | F7: 44978 | G7: 44980 | H7: Midlands | I7: Processing | J7: Ethan Williams | K7: Blank | N7: =PRODUCT(D7:E7) -> 346.85 | O7: =_xlfn.DAYS(G7,F7) -> 2 | P7: {=_xlfn.IFS(O7<4,"Speedy",O7<7,"Standard",O7>=7,"Slow")} -> Speedy | Q7: =TEXT(F7,"mmmm") -> February | R7: =TEXT(F7,"yyyy") -> 2023 | S7: =CONCATENATE(Q7," ",R7) -> February 2023 | T7: =_xlfn.XLOOKUP(B7,REF_Products!$A$2:$A$41,REF_Products!$C$2:$C$41) -> Health | V7: Scotland | W7: =_xlfn.XLOOKUP(REF_Regions!$K$1,REF_Regions!$I$1:$U$1,REF_Regions!I7:U7) -> 101733
A8: CUST007 | B8: PRD034 | C8: Business Strategy | D8: 3 | E8: 119.54 | F8: 45187 | G8: 45198 | H8: North England | I8: Cancelled | J8: Ali Morris | K8: Fragile | N8: =PRODUCT(D8:E8) -> 358.62 | O8: =_xlfn.DAYS(G8,F8) -> 11 | P8: {=_xlfn.IFS(O8<4,"Speedy",O8<7,"Standard",O8>=7,"Slow")} -> Slow | Q8: =TEXT(F8,"mmmm") -> September | R8: =TEXT(F8,"yyyy") -> 2023 | S8: =CONCATENATE(Q8," ",R8) -> September 2023 | T8: =_xlfn.XLOOKUP(B8,REF_Products!$A$2:$A$41,REF_Products!$C$2:$C$41) -> Books | V8: Wales | W8: =_xlfn.XLOOKUP(REF_Regions!$K$1,REF_Regions!$I$1:$U$1,REF_Regions!I8:U8) -> 80613
A9: CUST008 | B9: PRD002 | C9: Wireless Mouse | D9: 9 | E9: 149.61 | F9: 45149 | G9: 45151 | H9: Scotland | I9: Returned | J9: Jack Malik | K9: Express delivery | N9: =PRODUCT(D9:E9) -> 1346.49 | O9: =_xlfn.DAYS(G9,F9) -> 2 | P9: {=_xlfn.IFS(O9<4,"Speedy",O9<7,"Standard",O9>=7,"Slow")} -> Speedy | Q9: =TEXT(F9,"mmmm") -> August | R9: =TEXT(F9,"yyyy") -> 2023 | S9: =CONCATENATE(Q9," ",R9) -> August 2023 | T9: =_xlfn.XLOOKUP(B9,REF_Products!$A$2:$A$41,REF_Products!$C$2:$C$41) -> Electronics | V9: Northern Ireland | W9: =_xlfn.XLOOKUP(REF_Regions!$K$1,REF_Regions!$I$1:$U$1,REF_Regions!I9:U9) -> 49813
A10: CUST009 | B10: PRD039 | C10: T-Shirt Pack X3 | D10: 9 | E10: 210.01 | F10: 45248 | G10: 45258 | H10: North England | I10: Cancelled | J10: Zara Baker | K10: Leave at door | N10: =PRODUCT(D10:E10) -> 1890.09 | O10: =_xlfn.DAYS(G10,F10) -> 10 | P10: {=_xlfn.IFS(O10<4,"Speedy",O10<7,"Standard",O10>=7,"Slow")} -> Slow | Q10: =TEXT(F10,"mmmm") -> November | R10: =TEXT(F10,"yyyy") -> 2023 | S10: =CONCATENATE(Q10," ",R10) -> November 2023 | T10: =_xlfn.XLOOKUP(B10,REF_Products!$A$2:$A$41,REF_Products!$C$2:$C$41) -> Clothing
A11: CUST010 | B11: PRD031 | C11: Novel - The Shift | D11: 1 | E11: 156.5 | F11: 45214 | G11: 45216 | H11: South England | I11: Cancelled | J11: Hana Evans | K11: Gift wrap | N11: =PRODUCT(D11:E11) -> 156.5 | O11: =_xlfn.DAYS(G11,F11) -> 2 | P11: {=_xlfn.IFS(O11<4,"Speedy",O11<7,"Standard",O11>=7,"Slow")} -> Speedy | Q11: =TEXT(F11,"mmmm") -> October | R11: =TEXT(F11,"yyyy") -> 2023 | S11: =CONCATENATE(Q11," ",R11) -> October 2023 | T11: =_xlfn.XLOOKUP(B11,REF_Products!$A$2:$A$41,REF_Products!$C$2:$C$41) -> Books
A12: CUST011 | B12: PRD001 | C12: Laptop Pro 15 | D12: 1 | E12: 248.83 | F12: 45133 | G12: 45147 | H12: Northern Ireland | I12: Delivered | J12: Priya Khan | K12: Blank | N12: =PRODUCT(D12:E12) -> 248.83 | O12: =_xlfn.DAYS(G12,F12) -> 14 | P12: {=_xlfn.IFS(O12<4,"Speedy",O12<7,"Standard",O12>=7,"Slow")} -> Slow | Q12: =TEXT(F12,"mmmm") -> July | R12: =TEXT(F12,"yyyy") -> 2023 | S12: =CONCATENATE(Q12," ",R12) -> July 2023 | T12: =_xlfn.XLOOKUP(B12,REF_Products!$A$2:$A$41,REF_Products!$C$2:$C$41) -> Electronics
A13: CUST012 | B13: PRD035 | C13: Cook Book 2024 | D13: 2 | E13: 89.54 | F13: 45032 | G13: 45043 | H13: South England | I13: Returned | J13: Ali Roberts | K13: Express delivery | N13: =PRODUCT(D13:E13) -> 179.08 | O13: =_xlfn.DAYS(G13,F13) -> 11 | P13: {=_xlfn.IFS(O13<4,"Speedy",O13<7,"Standard",O13>=7,"Slow")} -> Slow | Q13: =TEXT(F13,"mmmm") -> April | R13: =TEXT(F13,"yyyy") -> 2023 | S13: =CONCATENATE(Q13," ",R13) -> April 2023 | T13: =_xlfn.XLOOKUP(B13,REF_Products!$A$2:$A$41,REF_Products!$C$2:$C$41) -> Books
A14: CUST013 | B14: PRD011 | C14: Whiteboard A1 | D14: 10 | E14: 72.28 | F14: 45062 | G14: 45072 | H14: Scotland | I14: Pending | J14: Luke Singh | K14: Express delivery | N14: =PRODUCT(D14:E14) -> 722.8 | O14: =_xlfn.DAYS(G14,F14) -> 10 | P14: {=_xlfn.IFS(O14<4,"Speedy",O14<7,"Standard",O14>=7,"Slow")} -> Slow | Q14: =TEXT(F14,"mmmm") -> May | R14: =TEXT(F14,"yyyy") -> 2023 | S14: =CONCATENATE(Q14," ",R14) -> May 2023 | T14: =_xlfn.XLOOKUP(B14,REF_Products!$A$2:$A$41,REF_Products!$C$2:$C$41) -> Stationery
A15: CUST014 | B15: PRD003 | C15: Usb-C Hub | D15: 4 | E15: 82.31 | F15: 45031 | G15: 45036 | H15: West England | I15: Processing | J15: George Cox | K15: Blank | N15: =PRODUCT(D15:E15) -> 329.24 | O15: =_xlfn.DAYS(G15,F15) -> 5 | P15: {=_xlfn.IFS(O15<4,"Speedy",O15<7,"Standard",O15>=7,"Slow")} -> Standard | Q15: =TEXT(F15,"mmmm") -> April | R15: =TEXT(F15,"yyyy") -> 2023 | S15: =CONCATENATE(Q15," ",R15) -> April 2023 | T15: =_xlfn.XLOOKUP(B15,REF_Products!$A$2:$A$41,REF_Products!$C$2:$C$41) -> Electronics
A16: CUST015 | B16: PRD025 | C16: Coffee Maker | D16: 2 | E16: 222.09 | F16: 45433 | G16: 45440 | H16: West England | I16: Cancelled | J16: Nina Walker | K16: Gift wrap | N16: =PRODUCT(D16:E16) -> 444.18 | O16: =_xlfn.DAYS(G16,F16) -> 7 | P16: {=_xlfn.IFS(O16<4,"Speedy",O16<7,"Standard",O16>=7,"Slow")} -> Slow | Q16: =TEXT(F16,"mmmm") -> May | R16: =TEXT(F16,"yyyy") -> 2024 | S16: =CONCATENATE(Q16," ",R16) -> May 2024 | T16: =_xlfn.XLOOKUP(B16,REF_Products!$A$2:$A$41,REF_Products!$C$2:$C$41) -> Kitchen
A17: CUST016 | B17: PRD006 | C17: Webcam Hd | D17: 3 | E17: 7.66 | F17: 45053 | G17: 45055 | H17: North England | I17: Cancelled | J17: Nadia Cooper | K17: Blank | N17: =PRODUCT(D17:E17) -> 22.98 | O17: =_xlfn.DAYS(G17,F17) -> 2 | P17: {=_xlfn.IFS(O17<4,"Speedy",O17<7,"Standard",O17>=7,"Slow")} -> Speedy | Q17: =TEXT(F17,"mmmm") -> May | R17: =TEXT(F17,"yyyy") -> 2023 | S17: =CONCATENATE(Q17," ",R17) -> May 2023 | T17: =_xlfn.XLOOKUP(B17,REF_Products!$A$2:$A$41,REF_Products!$C$2:$C$41) -> Electronics
A18: CUST017 | B18: PRD031 | C18: Novel - The Shift | D18: 2 | E18: 237.33 | F18: 45041 | G18: 45048 | H18: West England | I18: Delivered | J18: Daniel Gupta | K18: Blank | N18: =PRODUCT(D18:E18) -> 474.66 | O18: =_xlfn.DAYS(G18,F18) -> 7 | P18: {=_xlfn.IFS(O18<4,"Speedy",O18<7,"Standard",O18>=7,"Slow")} -> Slow | Q18: =TEXT(F18,"mmmm") -> April | R18: =TEXT(F18,"yyyy") -> 2023 | S18: =CONCATENATE(Q18," ",R18) -> April 2023 | T18: =_xlfn.XLOOKUP(B18,REF_Products!$A$2:$A$41,REF_Products!$C$2:$C$41) -> Books
A19: CUST018 | B19: PRD002 | C19: Wireless Mouse | D19: 1 | E19: 132.71 | F19: 45121 | G19: 45132 | H19: East England | I19: Cancelled | J19: James Singh | K19: Gift wrap | N19: =PRODUCT(D19:E19) -> 132.71 | O19: =_xlfn.DAYS(G19,F19) -> 11 | P19: {=_xlfn.IFS(O19<4,"Speedy",O19<7,"Standard",O19>=7,"Slow")} -> Slow | Q19: =TEXT(F19,"mmmm") -> July | R19: =TEXT(F19,"yyyy") -> 2023 | S19: =CONCATENATE(Q19," ",R19) -> July 2023 | T19: =_xlfn.XLOOKUP(B19,REF_Products!$A$2:$A$41,REF_Products!$C$2:$C$41) -> Electronics
A20: CUST019 | B20: PRD020 | C20: Water Bottle | D20: 1 | E20: 90.83 | F20: 45125 | G20: 45139 | H20: Wales | I20: Processing | J20: Noah Foster | K20: Blank | N20: =PRODUCT(D20:E20) -> 90.83 | O20: =_xlfn.DAYS(G20,F20) -> 14 | P20: {=_xlfn.IFS(O20<4,"Speedy",O20<7,"Standard",O20>=7,"Slow")} -> Slow | Q20: =TEXT(F20,"mmmm") -> July | R20: =TEXT(F20,"yyyy") -> 2023 | S20: =CONCATENATE(Q20," ",R20) -> July 2023 | T20: =_xlfn.XLOOKUP(B20,REF_Products!$A$2:$A$41,REF_Products!$C$2:$C$41) -> Sportswear
A21: CUST020 | B21: PRD008 | C21: Standing Desk | D21: 1 | E21: 119.57 | F21: 45005 | G21: 45012 | H21: Scotland | I21: Delivered | J21: Ethan King | K21: Fragile | N21: =PRODUCT(D21:E21) -> 119.57 | O21: =_xlfn.DAYS(G21,F21) -> 7 | P21: {=_xlfn.IFS(O21<4,"Speedy",O21<7,"Standard",O21>=7,"Slow")} -> Slow | Q21: =TEXT(F21,"mmmm") -> March | R21: =TEXT(F21,"yyyy") -> 2023 | S21: =CONCATENATE(Q21," ",R21) -> March 2023 | T21: =_xlfn.XLOOKUP(B21,REF_Products!$A$2:$A$41,REF_Products!$C$2:$C$41) -> Furniture
... A151: CUST150 | B151: PRD005 | C151: Monitor 27In | D151: 7 | E151: 64.15 | F151: 45291 | G151: 45293 | H151: East England | I151: Cancelled | J151: Sarah Cox | K151: Leave at door | N151: =PRODUCT(D151:E151) -> 449.05 | O151: =_xlfn.DAYS(G151,F151) -> 2 | P151: {=_xlfn.IFS(O151<4,"Speedy",O151<7,"Standard",O151>=7,"Slow")} -> Speedy | Q151: =TEXT(F151,"mmmm") -> December | R151: =TEXT(F151,"yyyy") -> 2023 | S151: =CONCATENATE(Q151," ",R151) -> December 2023 | T151: =_xlfn.XLOOKUP(B151,REF_Products!$A$2:$A$41,REF_Products!$C$2:$C$41) -> Electronics

Sheet Employees_Raw
A1: EmployeeID | B1: Full Name | C1: Department | D1: Hire Date | E1: Annual Salary | F1: Performance Score | G1: Email | H1: Contract Type | I1: Region
A2: EMP001 | B2: LUCAS COX | C2: Finance | D2: 44396 | E2: 33925 | F2: 1.2 | G2: lucas.cox@novamart.co.uk | H2: Apprenticeship | I2: scotland
A3: EMP002 | B3: Ben Jones | C3: Information Technology | D3: 03.06.2021 | E3: £27,508 | F3: 2.8 | G3: ben.jones@novamart.co.uk | H3: Permanent | I3: ni
A4: EMP003 | B4: jack wright | C4: I.T. | D4: 43793 | E4: £57268 | F4: 1 | G4: jack.wright@novamart.co.uk | H4: Fixed-Term | I4: Midlands
A5: EMP004 | B5: HARRY JONES | C5: Logis. | D5: 42061 | E5: 29057 | F5: 3.9 | G5: harry.jones@novamart.co.uk | H5: Contractor | I5: Mids
A6: EMP005 | B6: priya malik | C6: SALES | D6: 44600 | E6: 64232.00 | F6: 2.3 | G6: priya.malik@novamart.co.uk | H6: Apprenticeship | I6: north
A7: EMP006 | B7: Daniel Rao | C7: Operations | D7: 42176 | E7: 78337 | F7: 3.9 | G7: daniel.rao@novamart.co.uk | H7: Permanent | I7: wales
A8: EMP007 | B8: james cooper | D8: 42054 | E8: £48,539 | F8: 3.9 | G8: james.cooper@novamart.co.uk | H8: Part-Time | I8: scotland
A9: EMP008 | B9: Emma Johnson | C9: finance | D9: 42778 | E9: 58272.00 | F9: 1.7 | G9: emma.johnson@novamart.co.uk | H9: Contractor | I9: Scot.
A10: EMP009 | B10: Callum Adams | C10: Sales | D10: 42814 | E10: 48046 | F10: 1.2 | H10: Apprenticeship | I10: West
A11: EMP010 | B11: Zara Williams | D11: 22.07.2017 | E11: £79551 | F11: 2.4 | G11: zara.williams@novamart.co.uk | H11: Contractor | I11: MIDLANDS
A12: EMP011 | B12: Freya Wright | C12: OPERATIONS | D12: 42090 | E12: 54523.00 | F12: 2.5 | G12: freya.wright@novamart.co.uk | H12: Permanent | I12: WALES
A13: EMP012 | B13: Tara Bell | C13: Logis. | D13: 43301 | E13: £50,296 | F13: 3.9 | G13: tara.bell@novamart.co.uk | H13: Part-Time | I13: South
A14: EMP013 | B14: EMMA WRIGHT | C14: Sales | D14: 43679 | E14: 50386.00 | F14: 2.8 | G14: emma.wright@novamart.co.uk | H14: Apprenticeship | I14: ni
A15: EMP014 | B15: Sophie Smith | C15: logistics | D15: 42736 | E15: 55281 | F15: 4.7 | G15: sophie.smith@novamart.co.uk | H15: Contractor | I15: MIDLANDS
A16: EMP015 | B16: Lily Singh | C16: Sales | D16: 44748 | E16: 59209 | F16: 4.7 | G16: lily.singh@novamart.co.uk | H16: Apprenticeship | I16: wales
A17: EMP016 | B17: max wright | C17: LOGISTICS | D17: 42380 | E17: 26839 | F17: 1.4 | G17: max.wright@novamart.co.uk | H17: Fixed-Term | I17: WALES
A18: EMP017 | B18: Isla Khan | C18: Operations | D18: 42770 | E18: 32622.00 | F18: 3.8 | G18: isla.khan@novamart.co.uk | H18: Apprenticeship | I18: East
A19: EMP018 | B19: JESS DAVIES | C19: CUSTOMER SERVICE | D19: 43189 | E19: 65731 | F19: 2.8 | H19: Fixed-Term | I19: Scotland
A20: EMP019 | B20: BEN GUPTA | C20: CUSTOMER SERVICE | D20: 44269 | E20: 73090 | F20: 3 | G20: ben.gupta@novamart.co.uk | H20: Permanent | I20: East
A21: EMP020 | B21: Noah Wright | C21: Ops | D21: 21.06.2021 | E21: 42583 | F21: 1.5 | G21: noah.wright@novamart.co.uk | H21: Part-Time | I21: scotland
A22: EMP021 | B22: daniel ahmed | C22: Fin. | D22: 42392 | E22: £64,254 | F22: 1 | G22: daniel.ahmed@novamart.co.uk | H22: Part-Time | I22: NORTH
A23: EMP022 | B23: James Ali | C23: MARKETING | D23: 44941 | E23: 31586.00 | F23: 2.4 | G23: james.ali@novamart.co.uk | H23: Fixed-Term | I23: North
A24: EMP023 | B24: lucas baker | C24: HR | D24: 43259 | E24: £30,167 | F24: 1.5 | G24: lucas.baker@novamart.co.uk | H24: Fixed-Term | I24: Northern Ireland
A25: EMP024 | B25: Ryan Khan | C25: Human Res. | D25: 43454 | E25: 33140 | F25: 3.9 | G25: ryan.khan@novamart.co.uk | H25: Part-Time | I25: wales
A26: EMP025 | B26: Nadia Jones | C26: OPERATIONS | D26: 44420 | E26: 24971 | F26: 2.7 | G26: nadia.jones@novamart.co.uk | H26: Part-Time | I26: East
A27: EMP026 | B27: Isla Williams | C27: Customer Service | D27: 43464 | E27: £78,449 | F27: 2.7 | G27: isla.williams@novamart.co.uk | H27: Part-Time | I27: Scot.
A28: EMP027 | B28: Sophie Cox | C28: Marketing | D28: 42144 | E28: £51561 | F28: 2.2 | G28: sophie.cox@novamart.co.uk | H28: Permanent | I28: west
A29: EMP028 | B29: Jack Williams | C29: Ops | D29: 43478 | E29: £70151 | F29: 2.2 | G29: jack.williams@novamart.co.uk | H29: Part-Time | I29: ni
A30: EMP029 | B30: FINN REED | C30: Customer Service | D30: 42662 | E30: £50,347 | F30: 1.2 | G30: finn.reed@novamart.co.uk | H30: Part-Time | I30: ni
A31: EMP030 | B31: Fatima Sharma | D31: 43685 | F31: 1.8 | G31: fatima.sharma@novamart.co.uk | H31: Contractor | I31: Wales
A32: EMP031 | B32: Amy Green | C32: Sales | D32: 45262 | E32: 51265 | F32: 4.5 | H32: Fixed-Term | I32: Scotland
A33: EMP032 | B33: Nadia Scott | C33: HR | D33: 42887 | E33: £47856 | F33: 1.9 | G33: nadia.scott@novamart.co.uk | H33: Permanent | I33: midlands
A34: EMP033 | B34: NOAH DAVIES | C34: Cust. Service | D34: 44989 | E34: 60847 | F34: 1.5 | G34: noah.davies@novamart.co.uk | H34: Contractor | I34: South
A35: EMP034 | B35: Liam Wright | C35: Fin. | D35: 14.09.2020 | E35: 37679 | F35: 2.2 | G35: liam.wright@novamart.co.uk | H35: Permanent | I35: South
A36: EMP035 | B36: isla walker | C36: Operations | D36: 44166 | E36: 58847 | F36: 4.3 | G36: isla.walker@novamart.co.uk | H36: Apprenticeship | I36: NORTH
A37: EMP036 | B37: Mohammed Morris | C37: LOGISTICS | D37: 43181 | E37: £73,429 | F37: 1.4 | G37: mohammed.morris@novamart.co.uk | H37: Part-Time | I37: Scot.
A38: EMP037 | B38: Nadia Jones | C38: CUSTOMER SERVICE | D38: 19.11.2022 | E38: 51381 | F38: 1.7 | G38: nadia.jones@novamart.co.uk | H38: Permanent | I38: east
A39: EMP038 | B39: george khan | C39: Logis. | D39: 44685 | E39: 71396 | F39: 2.9 | G39: george.khan@novamart.co.uk | H39: Apprenticeship | I39: East
A40: EMP039 | B40: GRACE HUSSAIN | C40: I.T. | D40: 44026 | E40: 61045 | F40: 2 | G40: grace.hussain@novamart.co.uk | H40: Contractor | I40: south
A41: EMP040 | B41: Nina Rao | C41: marketing | D41: 43414 | E41: 31607 | F41: 1.9 | G41: nina.rao@novamart.co.uk | H41: Fixed-Term | I41: SCOTLAND
A42: EMP041 | B42: Adam Thomas | C42: Cust. Service | D42: 43555 | E42: 69282 | F42: 1.8 | G42: adam.thomas@novamart.co.uk | H42: Permanent | I42: north
A43: EMP042 | B43: Priya Murphy | C43: OPERATIONS | D43: 44127 | E43: £42,236 | F43: 2.8 | G43: priya.murphy@novamart.co.uk | H43: Fixed-Term | I43: south
A44: EMP043 | B44: Ryan Green | C44: Ops | D44: 42950 | E44: £72,651 | F44: 3.1 | G44: ryan.green@novamart.co.uk | H44: Part-Time | I44: ni
A45: EMP044 | B45: Harry Scott | C45: LOGISTICS | D45: 44691 | E45: 39364 | F45: 2 | G45: harry.scott@novamart.co.uk | H45: Apprenticeship | I45: Scot.
A46: EMP045 | B46: mia ward | C46: finance | D46: 43975 | E46: £59911 | F46: 1.8 | G46: mia.ward@novamart.co.uk | H46: Permanent | I46: WALES
A47: EMP046 | B47: Olivia Ahmed | C47: it | D47: 42286 | E47: £47122 | F47: 1.5 | G47: olivia.ahmed@novamart.co.uk | H47: Permanent | I47: North
A48: EMP047 | B48: Amelia Davies | C48: SALES | D48: 43851 | E48: 66451 | F48: 4.2 | G48: amelia.davies@novamart.co.uk | H48: Fixed-Term | I48: Northern Ireland
A49: EMP048 | B49: Emma Bailey | C49: Mktg | D49: 44695 | E49: 70740 | F49: 3.4 | G49: emma.bailey@novamart.co.uk | H49: Permanent | I49: WALES
A50: EMP049 | B50: Sarah Walker | C50: FINANCE | D50: 12.08.2017 | E50: 70632.00 | F50: 1.9 | H50: Permanent | I50: west
A51: EMP050 | B51: owen baker | C51: it | D51: 42735 | E51: £75920 | F51: 4 | G51: owen.baker@novamart.co.uk | H51: Contractor | I51: Scot.
A52: EMP051 | B52: ravi king | C52: Sales | D52: 24.07.2021 | E52: 47604.00 | F52: 3.1 | H52: Contractor | I52: west
A53: EMP052 | B53: jack morris | C53: SALES | D53: 43498 | E53: £38686 | F53: 4 | G53: jack.morris@novamart.co.uk | H53: Part-Time | I53: west
A54: EMP053 | B54: olivia baker | C54: SALES | D54: 10.09.2020 | E54: 53984 | F54: 2.9 | G54: olivia.baker@novamart.co.uk | H54: Fixed-Term | I54: Scotland
A55: EMP054 | B55: HARRY SINGH | C55: customer service | D55: 44034 | E55: £74160 | F55: 3.7 | G55: harry.singh@novamart.co.uk | H55: Apprenticeship | I55: East
A56: EMP055 | B56: TARA JOHNSON | C56: LOGISTICS | D56: 16.03.2018 | E56: 61414 | F56: 2.9 | G56: tara.johnson@novamart.co.uk | H56: Apprenticeship | I56: EAST
A57: EMP056 | B57: Sarah Taylor | C57: Logis. | D57: 21.02.2023 | E57: 31072 | F57: 3.8 | G57: sarah.taylor@novamart.co.uk | H57: Part-Time | I57: West
A58: EMP057 | B58: Jess Taylor | C58: Cust. Service | D58: 44299 | E58: 74808 | F58: 2.2 | G58: jess.taylor@novamart.co.uk | H58: Apprenticeship | I58: North
A59: EMP058 | B59: noah bailey | C59: SALES | D59: 05.01.2022 | E59: £69,388 | F59: 1.7 | G59: noah.bailey@novamart.co.uk | H59: Permanent | I59: Mids
A60: EMP059 | B60: Ryan Bell | C60: Customer Service | D60: 42792 | E60: 45514.00 | F60: 3.2 | G60: ryan.bell@novamart.co.uk | H60: Permanent | I60: Mids
A61: EMP060 | B61: OLIVIA WRIGHT | C61: HR | D61: 42335 | E61: 29897 | F61: 1.3 | G61: olivia.wright@novamart.co.uk | H61: Part-Time | I61: Scotland
A62: EMP061 | B62: freya walker | C62: finance | D62: 43406 | E62: 72809.00 | F62: 4.3 | G62: freya.walker@novamart.co.uk | H62: Fixed-Term | I62: east
A63: EMP062 | B63: Priya Cooper | C63: Ops | D63: 22.01.2021 | E63: 78671 | F63: 2.9 | G63: priya.cooper@novamart.co.uk | H63: Permanent | I63: WALES
A64: EMP063 | B64: sophie williams | C64: Customer Service | D64: 44592 | E64: £34,189 | F64: 2 | G64: sophie.williams@novamart.co.uk | H64: Contractor | I64: NORTH
A65: EMP064 | B65: Freya Hussain | C65: Marketing | D65: 44422 | E65: 65186.00 | F65: 2.2 | G65: freya.hussain@novamart.co.uk | H65: Apprenticeship | I65: south
A66: EMP065 | B66: Sam Wilson | C66: Finance | D66: 42238 | E66: £30971 | F66: 4.5 | G66: sam.wilson@novamart.co.uk | H66: Apprenticeship | I66: West
A67: EMP066 | B67: james cooper | C67: Sales | D67: 23.08.2017 | E67: 41048.00 | F67: 3.9 | G67: james.cooper@novamart.co.uk | H67: Part-Time | I67: ni
A68: EMP067 | B68: Finn Hussain | C68: LOGISTICS | D68: 29.12.2016 | E68: 59280 | F68: 4.9 | H68: Apprenticeship | I68: scotland
A69: EMP068 | B69: nina clarke | C69: CUSTOMER SERVICE | D69: 42752 | E69: £25648 | F69: 1.6 | G69: nina.clarke@novamart.co.uk | H69: Permanent | I69: east
A70: EMP069 | B70: LUKE SMITH | C70: it | D70: 06.09.2016 | E70: 54915 | F70: 2.9 | G70: luke.smith@novamart.co.uk | H70: Fixed-Term | I70: NI
A71: EMP070 | B71: Tara Ali | C71: FINANCE | D71: 11.02.2021 | E71: £37,679 | F71: 2.4 | G71: tara.ali@novamart.co.uk | H71: Contractor | I71: MIDLANDS
A72: EMP071 | B72: George King | C72: CUSTOMER SERVICE | D72: 43615 | E72: 67033.00 | F72: 3.6 | G72: george.king@novamart.co.uk | H72: Fixed-Term | I72: ni
A73: EMP072 | B73: Ravi Williams | C73: I.T. | D73: 19.02.2018 | E73: 49300 | F73: 1.2 | G73: ravi.williams@novamart.co.uk | H73: Part-Time | I73: Midlands
A74: EMP073 | B74: Maya Rao | C74: Information Technology | D74: 44676 | E74: £50969 | F74: 4.9 | G74: maya.rao@novamart.co.uk | H74: Fixed-Term | I74: midlands
A75: EMP074 | B75: OWEN WARD | C75: customer service | D75: 44187 | E75: 63234 | F75: 2.4 | G75: owen.ward@novamart.co.uk | H75: Fixed-Term | I75: Mids
A76: EMP075 | B76: luke thomas | C76: Operations | D76: 42366 | E76: 49207.00 | F76: 2.9 | G76: luke.thomas@novamart.co.uk | H76: Permanent | I76: east
A77: EMP076 | B77: James Morris | C77: Ops | D77: 03.10.2016 | E77: £71082 | F77: 4.8 | H77: Apprenticeship | I77: Scotland
A78: EMP077 | B78: Luke Bell | C78: it | D78: 43311 | E78: £50,955 | F78: 3.2 | H78: Apprenticeship | I78: SOUTH
A79: EMP078 | B79: ravi malik | C79: Logis. | D79: 42613 | E79: 34583 | F79: 4.6 | G79: ravi.malik@novamart.co.uk | H79: Part-Time | I79: N.I.
A80: EMP079 | B80: Maya Adams | C80: OPERATIONS | D80: 12.05.2022 | E80: £69803 | F80: 4.4 | G80: maya.adams@novamart.co.uk | H80: Apprenticeship | I80: WALES
A81: EMP080 | B81: Daniel Wright | C81: Fin. | D81: 17.02.2018 | E81: 22374 | F81: 2.5 | G81: daniel.wright@novamart.co.uk | H81: Permanent | I81: West
A82: EMP012 | B82: Tara Bell | C82: Logis. | D82: 43301 | E82: £50,296 | F82: 3.9 | G82: tara.bell@novamart.co.uk | H82: Part-Time | I82: South
A83: EMP066 | B83: james cooper | C83: Sales | D83: 23.08.2017 | E83: 41048.00 | F83: 3.9 | G83: james.cooper@novamart.co.uk | H83: Part-Time | I83: ni
A84: EMP018 | B84: JESS DAVIES | C84: CUSTOMER SERVICE | D84: 43189 | E84: 65731 | F84: 2.8 | H84: Fixed-Term | I84: Scotland

Sheet Employees_Clean
A1: EmployeeID | B1: Full Name | C1: Department | D1: Hire Date | E1: Annual Salary | F1: Performance Score | G1: Email | H1: Contract Type | I1: Region | K1: Formulas | L1: Performance Score 2 | M1: Job Grade, Manager, and Office Location | P1: Manager Vlookup
A2: EMP001 | B2: Lucas Cox | C2: Finance | D2: 44396 | E2: 33925 | F2: 1.2 | G2: lucas.cox@novamart.co.uk | H2: Apprenticeship | I2: Scotland | L2: {=_xlfn.IFS(F2<=2,"Poor",F2<3,"Marginal",F2<4,"Good",F2>=4,"Excellent")} -> Poor | M2: {=_xlfn.XLOOKUP(A2,REF_Employees!A2:A84,REF_Employees!C2:E84)} -> Director | N2: J. Carter | O2: Birmingham | P2: =VLOOKUP(A2,REF_Employees!A2:D84,4) -> J. Carter
A3: EMP002 | B3: Ben Jones | C3: IT | D3: 44350 | E3: 27508 | F3: 2.8 | G3: ben.jones@novamart.co.uk | H3: Permanent | I3: Northern Ireland | L3: {=_xlfn.IFS(F3<=2,"Poor",F3<3,"Marginal",F3<4,"Good",F3>=4,"Excellent")} -> Marginal | M3: {=_xlfn.XLOOKUP(A3,REF_Employees!A3:A82,REF_Employees!C3:E82)} -> Senior | N3: T. Williams | O3: Belfast | P3: =VLOOKUP(A3,REF_Employees!A3:D85,4) -> T. Williams
A4: EMP003 | B4: Jack Wright | C4: IT | D4: 43793 | E4: 57268 | F4: 1 | G4: jack.wright@novamart.co.uk | H4: Fixed-Term | I4: Midlands | L4: {=_xlfn.IFS(F4<=2,"Poor",F4<3,"Marginal",F4<4,"Good",F4>=4,"Excellent")} -> Poor | M4: {=_xlfn.XLOOKUP(A4,REF_Employees!A4:A83,REF_Employees!C4:E83)} -> Senior | N4: R. Okafor | O4: Birmingham | P4: =VLOOKUP(A4,REF_Employees!A4:D86,4) -> R. Okafor
A5: EMP004 | B5: Harry Jones | C5: Logistics | D5: 42061 | E5: 29057 | F5: 3.9 | G5: harry.jones@novamart.co.uk | H5: Contractor | I5: Midlands | L5: {=_xlfn.IFS(F5<=2,"Poor",F5<3,"Marginal",F5<4,"Good",F5>=4,"Excellent")} -> Good | M5: {=_xlfn.XLOOKUP(A5,REF_Employees!A5:A84,REF_Employees!C5:E84)} -> Senior | N5: T. Williams | O5: Edinburgh | P5: =VLOOKUP(A5,REF_Employees!A5:D87,4) -> T. Williams
A6: EMP005 | B6: Priya Malik | C6: Sales | D6: 44600 | E6: 64232 | F6: 2.3 | G6: priya.malik@novamart.co.uk | H6: Apprenticeship | I6: North England | L6: {=_xlfn.IFS(F6<=2,"Poor",F6<3,"Marginal",F6<4,"Good",F6>=4,"Excellent")} -> Marginal | M6: {=_xlfn.XLOOKUP(A6,REF_Employees!A6:A85,REF_Employees!C6:E85)} -> Manager | N6: S. Hughes | O6: Belfast | P6: =VLOOKUP(A6,REF_Employees!A6:D88,4) -> S. Hughes
A7: EMP006 | B7: Daniel Rao | C7: Operations | D7: 42176 | E7: 78337 | F7: 3.9 | G7: daniel.rao@novamart.co.uk | H7: Permanent | I7: Wales | L7: {=_xlfn.IFS(F7<=2,"Poor",F7<3,"Marginal",F7<4,"Good",F7>=4,"Excellent")} -> Good | M7: {=_xlfn.XLOOKUP(A7,REF_Employees!A7:A86,REF_Employees!C7:E86)} -> Junior | N7: S. Hughes | O7: Manchester | P7: =VLOOKUP(A7,REF_Employees!A7:D89,4) -> S. Hughes
A8: EMP007 | B8: James Cooper | C8: N/A | D8: 42054 | E8: 48539 | F8: 3.9 | G8: james.cooper@novamart.co.uk | H8: Part-Time | I8: Scotland | L8: {=_xlfn.IFS(F8<=2,"Poor",F8<3,"Marginal",F8<4,"Good",F8>=4,"Excellent")} -> Good | M8: {=_xlfn.XLOOKUP(A8,REF_Employees!A8:A87,REF_Employees!C8:E87)} -> Junior | N8: L. Bennett | O8: Cardiff | P8: =VLOOKUP(A8,REF_Employees!A8:D90,4) -> L. Bennett
A9: EMP008 | B9: Emma Johnson | C9: Finance | D9: 42778 | E9: 58272 | F9: 1.7 | G9: emma.johnson@novamart.co.uk | H9: Contractor | I9: Scotland | L9: {=_xlfn.IFS(F9<=2,"Poor",F9<3,"Marginal",F9<4,"Good",F9>=4,"Excellent")} -> Poor | M9: {=_xlfn.XLOOKUP(A9,REF_Employees!A9:A88,REF_Employees!C9:E88)} -> Senior | N9: A. Singh | O9: Cardiff | P9: =VLOOKUP(A9,REF_Employees!A9:D91,4) -> A. Singh
A10: EMP009 | B10: Callum Adams | C10: Sales | D10: 42814 | E10: 48046 | F10: 1.2 | G10: N/A | H10: Apprenticeship | I10: West England | L10: {=_xlfn.IFS(F10<=2,"Poor",F10<3,"Marginal",F10<4,"Good",F10>=4,"Excellent")} -> Poor | M10: {=_xlfn.XLOOKUP(A10,REF_Employees!A10:A89,REF_Employees!C10:E89)} -> Lead | N10: A. Singh | O10: Edinburgh | P10: =VLOOKUP(A10,REF_Employees!A10:D92,4) -> A. Singh
A11: EMP010 | B11: Zara Williams | C11: N/A | D11: 42938 | E11: 79551 | F11: 2.4 | G11: zara.williams@novamart.co.uk | H11: Contractor | I11: Midlands | L11: {=_xlfn.IFS(F11<=2,"Poor",F11<3,"Marginal",F11<4,"Good",F11>=4,"Excellent")} -> Marginal | M11: {=_xlfn.XLOOKUP(A11,REF_Employees!A11:A90,REF_Employees!C11:E90)} -> Senior | N11: A. Singh | O11: Edinburgh | P11: =VLOOKUP(A11,REF_Employees!A11:D93,4) -> A. Singh
A12: EMP011 | B12: Freya Wright | C12: Operations | D12: 42090 | E12: 54523 | F12: 2.5 | G12: freya.wright@novamart.co.uk | H12: Permanent | I12: Wales | L12: {=_xlfn.IFS(F12<=2,"Poor",F12<3,"Marginal",F12<4,"Good",F12>=4,"Excellent")} -> Marginal | M12: {=_xlfn.XLOOKUP(A12,REF_Employees!A12:A91,REF_Employees!C12:E91)} -> Senior | N12: A. Singh | O12: Cardiff | P12: =VLOOKUP(A12,REF_Employees!A12:D94,4) -> A. Singh
A13: EMP012 | B13: Tara Bell | C13: Logistics | D13: 43301 | E13: 50296 | F13: 3.9 | G13: tara.bell@novamart.co.uk | H13: Part-Time | I13: South England | L13: {=_xlfn.IFS(F13<=2,"Poor",F13<3,"Marginal",F13<4,"Good",F13>=4,"Excellent")} -> Good | M13: {=_xlfn.XLOOKUP(A13,REF_Employees!A13:A92,REF_Employees!C13:E92)} -> Lead | N13: A. Singh | O13: Belfast | P13: =VLOOKUP(A13,REF_Employees!A13:D95,4) -> A. Singh
A14: EMP013 | B14: Tara Bell | C14: Logistics | D14: 43301 | E14: 50386 | F14: 3.9 | G14: tara.bell@novamart.co.uk | H14: Part-Time | I14: South England | L14: {=_xlfn.IFS(F14<=2,"Poor",F14<3,"Marginal",F14<4,"Good",F14>=4,"Excellent")} -> Good | M14: {=_xlfn.XLOOKUP(A14,REF_Employees!A14:A93,REF_Employees!C14:E93)} -> Manager | N14: T. Williams | O14: London | P14: =VLOOKUP(A14,REF_Employees!A14:D96,4) -> T. Williams
... A84: EMP083 | B84: Daniel Wright | C84: Finance | D84: 43148 | E84: 65731 | F84: 2.5 | G84: daniel.wright@novamart.co.uk | H84: Permanent | I84: West England | L84: {=_xlfn.IFS(F84<=2,"Poor",F84<3,"Marginal",F84<4,"Good",F84>=4,"Excellent")} -> Marginal | M84: {=_xlfn.XLOOKUP(A84,REF_Employees!A84:A163,REF_Employees!C84:E163)} -> Manager | N84: J. Carter | O84: Manchester | P84: =VLOOKUP(A84,REF_Employees!A84:D166,4) -> J. Carter

Sheet Products_Raw
A1: ProductID | B1: Product Name | C1: Category | D1: Stock Level | E1: Reorder Level | F1: Active
A2: PRD001 | B2: Laptop Pro 15 | C2: Elec. | D2: 136 | E2: 11 | F2: No
A3: PRD002 | B3: Wireless Mouse | C3: Electronics | D3: 120 | E3: 22 | F3: YES
A4: PRD003 | B4: USB-C HUB | C4: ELECTRONICS | D4: 55 | E4: 13 | F4: YES
A5: PRD004 | B5: Mechanical Keyboard | C5: Electronics | D5: 198 | E5: 7 | F5: yes
A6: PRD005 | B6: MONITOR 27IN | C6: electronics | D6: 167 | E6: 11 | F6: yes
A7: PRD006 | B7: WEBCAM HD | C7: electronics | D7: 57 | E7: 10 | F7: No
A8: PRD007 | B8: OFFICE CHAIR | C8: FURNITURE | D8: 50 | E8: 9 | F8: yes
A9: PRD008 | B9: STANDING DESK | C9: furniture | D9: 182 | E9: 15 | F9: no
A10: PRD009 | B10: Desk Lamp | C10: Furniture | D10: 54 | E10: 25 | F10: TRUE
A11: PRD010 | B11: filing cabinet | C11: furniture | D11: 62 | E11: 30 | F11: yes
A12: PRD011 | B12: Whiteboard A1 | C12: stationery | D12: 35 | E12: 6 | F12: yes
A13: PRD012 | B13: Notebook Pack | C13: Stationery | D13: 0 | E13: 12 | F13: yes
... A41: PRD040 | B41: Trainers Size 9 | C41: Apparel | D41: 95 | E41: 30 | F41: FALSE

Sheet Products_Clean
A1: ProductID | B1: Product Name | C1: Category | D1: Stock Level | E1: Reorder Level | F1: Active
A2: PRD001 | B2: Laptop Pro 15 | C2: Electronics | D2: 136 | E2: 11 | F2: No
A3: PRD002 | B3: Wireless Mouse | C3: Electronics | D3: 120 | E3: 22 | F3: Yes
A4: PRD003 | B4: Usb-C Hub | C4: Electronics | D4: 55 | E4: 13 | F4: Yes
A5: PRD004 | B5: Mechanical Keyboard | C5: Electronics | D5: 198 | E5: 7 | F5: Yes
A6: PRD005 | B6: Monitor 27In | C6: Electronics | D6: 167 | E6: 11 | F6: Yes
A7: PRD006 | B7: Webcam Hd | C7: Electronics | D7: 57 | E7: 10 | F7: No
A8: PRD007 | B8: Office Chair | C8: Furniture | D8: 50 | E8: 9 | F8: Yes
A9: PRD008 | B9: Standing Desk | C9: Furniture | D9: 182 | E9: 15 | F9: No
A10: PRD009 | B10: Desk Lamp | C10: Furniture | D10: 54 | E10: 25 | F10: Yes
A11: PRD010 | B11: Filing Cabinet | C11: Furniture | D11: 62 | E11: 30 | F11: Yes
A12: PRD011 | B12: Whiteboard A1 | C12: Stationery | D12: 35 | E12: 6 | F12: Yes
A13: PRD012 | B13: Notebook Pack | C13: Stationery | D13: 0 | E13: 12 | F13: Yes
... A41: PRD040 | B41: Trainers Size 9 | C41: Apparel | D41: 95 | E41: 30 | F41: No

Sheet Returns_Raw
A1: ReturnID | B1: ProductID | C1: Return Date | D1: Reason | E1: Refund Amount | F1: Resolved | G1: Days to Resolve
A2: RET001 | B2: PRD034 | C2: 13.12.2023 | E2: 79.03 | F2: yes | G2: 19
A3: RET002 | B3: PRD011 | C3: 02.04.2023 | E3: 49.47 | F3: yes | G3: 11
A4: RET003 | B4: PRD010 | C4: 30/03/2024 | D4: Defective | E4: 103.68 | F4: Pending | G4: 19
A5: RET004 | B5: PRD004 | C5: 16.11.2023 | D5: Damaged | E5: 66.55 | F5: no | G5: 6
A6: RET005 | B6: PRD007 | C6: 18.01.2024 | D6: Changed mind | E6: $225.68 | F6: Pending | G6: 10
A7: RET006 | B7: PRD019 | C7: 04.07.2023 | D7: Too large | E7: $29.39 | F7: no | G7: 15
A8: RET007 | B8: PRD019 | C8: 19.08.2023 | D8: Wrong item | E8: 34.34 | F8: yes | G8: 15
A9: RET008 | B9: PRD007 | C9: 2023-03-30 | D9: Not as described | E9: £9.80 | F9: Yes | G9: 20
A10: RET009 | B10: PRD022 | C10: 01.12.2023 | D10: Changed mind | E10: $86.41 | F10: yes | G10: 18
A11: RET010 | B11: PRD039 | C11: 17-Jan-2023 | E11: £111.71 | F11: No | G11: 11
A12: RET011 | B12: PRD004 | C12: 2023-06-16 | D12: Duplicate order | E12: 288.26 | F12: YES | G12: 3
A13: RET012 | B13: PRD035 | C13: 03-Sep-2023 | D13: Not as described | E13: £62.71 | F13: No | G13: 13
A14: RET013 | B14: PRD012 | C14: 21/01/2023 | D14: Damaged | E14: $204.30 | F14: Yes | G14: 20
A15: RET014 | B15: PRD020 | C15: 23-Feb-2023 | D15: Changed mind | E15: $153.42 | F15: Pending | G15: 4
A16: RET015 | B16: PRD037 | C16: August 07 2023 | E16: $53.56 | F16: YES | G16: 18
A17: RET016 | B17: PRD034 | C17: 08-Jan-2024 | D17: Duplicate order | E17: £282.52 | F17: Pending | G17: 5
A18: RET017 | B18: PRD024 | C18: 2023-03-16 | D18: Too large | E18: $99.99 | F18: Pending | G18: 7
A19: RET018 | B19: PRD034 | C19: 30.07.2023 | D19: Damaged | E19: £224.38 | F19: Pending | G19: 12
A20: RET019 | B20: PRD001 | C20: 01-May-2024 | D20: Defective | E20: £165.60 | F20: No | G20: 6
A21: RET020 | B21: PRD035 | C21: 2023-09-29 | D21: Defective | E21: £160.28 | F21: yes | G21: 11
A22: RET021 | B22: PRD012 | C22: 15-Nov-2023 | D22: Changed mind | E22: 146.41 | F22: No | G22: 6
A23: RET022 | B23: PRD014 | C23: 28.01.2024 | D23: Not as described | E23: £106.89 | F23: Yes | G23: 12
A24: RET023 | B24: PRD004 | C24: 15.08.2023 | D24: Wrong item | E24: £88.09 | F24: No | G24: 10
A25: RET024 | B25: PRD026 | C25: June 03 2023 | D25: Wrong item | E25: £180.30 | F25: Yes | G25: 18
A26: RET025 | B26: PRD008 | C26: 19/11/2023 | D26: Not as described | E26: 52.19 | F26: No | G26: 21
A27: RET026 | B27: PRD037 | C27: 13-Apr-2023 | D27: Defective | E27: $296.82 | F27: no | G27: 11
A28: RET027 | B28: PRD027 | C28: April 15 2024 | D28: Not as described | E28: £3.39 | F28: no | G28: 21
... A31: RET030 | B31: PRD023 | C31: 05.03.2024 | D31: Too small | E31: £83.23 | F31: no | G31: 12
A32: RET031 | B32: PRD030 | C32: June 15 2023 | E32: £36.63 | F32: Pending | G32: 11
A33: RET032 | B33: PRD035 | C33: July 30 2023 | D33: Wrong item | E33: £193.21 | F33: Pending | G33: 21
A34: RET033 | B34: PRD007 | C34: 22/06/2024 | D34: Not as described | E34: 155.47 | F34: yes | G34: 4
A35: RET034 | B35: PRD018 | C35: July 04 2023 | D35: Too small | E35: 77.11 | F35: Pending | G35: 18
A36: RET035 | B36: PRD012 | C36: October 11 2023 | D36: Defective | E36: 26.68 | F36: Pending | G36: 16
A37: RET036 | B37: PRD010 | C37: 2023-07-17 | D37: Too small | E37: £16.94 | F37: yes | G37: 1
A38: RET037 | B38: PRD023 | C38: June 04 2024 | D38: Wrong item | E38: £93.71 | F38: YES | G38: 5
A39: RET038 | B39: PRD004 | C39: 28-Nov-2023 | D39: Damaged | E39: 24.61 | F39: Pending | G39: 9
A40: RET039 | B40: PRD036 | C40: 2024-01-05 | D40: Too small | E40: £103.31 | F40: no | G40: 9
A41: RET040 | B41: PRD036 | C41: 19/03/2024 | D41: Too large | E41: 114.13 | F41: Yes | G41: 19
A42: RET041 | B42: PRD004 | C42: June 10 2023 | D42: Wrong item | E42: 214.56 | F42: Pending | G42: 6
A43: RET042 | B43: PRD028 | C43: December 20 2023 | D43: Too large | E43: £257.54 | F43: no | G43: 11
A44: RET043 | B44: PRD029 | C44: 15.09.2023 | D44: Wrong item | E44: £217.64 | F44: yes | G44: 9
... A51: RET050 | B51: PRD029 | C51: 11/01/2024 | D51: Duplicate order | E51: £19.20 | F51: YES | G51: 8

Sheet Returns_Clean
A1: ReturnID | B1: ProductID | C1: Return Date | D1: Reason | E1: Refund Amount | F1: Resolved | G1: Days to Resolve
A2: RET001 | B2: PRD034 | C2: 45273 | D2: Unknown | E2: 79.03 | F2: Yes | G2: 19
A3: RET002 | B3: PRD011 | C3: 45018 | D3: Unknown | E3: 49.47 | F3: Yes | G3: 11
A4: RET003 | B4: PRD010 | C4: 45381 | D4: Defective | E4: 103.68 | F4: Pending | G4: 19
A5: RET004 | B5: PRD004 | C5: 45246 | D5: Damaged | E5: 66.55 | F5: No | G5: 6
A6: RET005 | B6: PRD007 | C6: 45309 | D6: Changed mind | E6: 225.68 | F6: Pending | G6: 10
A7: RET006 | B7: PRD019 | C7: 45111 | D7: Too large | E7: 29.39 | F7: No | G7: 15
A8: RET007 | B8: PRD019 | C8: 45157 | D8: Wrong item | E8: 34.34 | F8: Yes | G8: 15
A9: RET008 | B9: PRD007 | C9: 45015 | D9: Not as described | E9: 9.8 | F9: Yes | G9: 20
A10: RET009 | B10: PRD022 | C10: 45261 | D10: Changed mind | E10: 86.41 | F10: Yes | G10: 18
A11: RET010 | B11: PRD039 | C11: 44943 | D11: Unknown | E11: 111.71 | F11: No | G11: 11
A12: RET011 | B12: PRD004 | C12: 45093 | D12: Duplicate order | E12: 288.26 | F12: Yes | G12: 3
A13: RET012 | B13: PRD035 | C13: 45172 | D13: Not as described | E13: 62.71 | F13: No | G13: 13
... A51: RET050 | B51: PRD029 | C51: 45302 | D51: Duplicate order | E51: 19.2 | F51: Yes | G51: 8

Sheet REF_Regions
A1: Region Code | B1: Full Region Name | C1: Regional Manager | D1: Sales Target £ | E1: Population (m) | F1: Active | H1: Monthly Targets | I1: Region | J1: Jan | K1: Feb | L1: Mar | M1: Apr | N1: May | O1: Jun | P1: Jul | Q1: Aug | R1: Sep | S1: Oct | T1: Nov | U1: Dec
A2: North | B2: North England | C2: J. Carter | D2: 850000 | E2: 8.2 | F2: Yes | I2: North England | J2: 113047 | K2: 72740 | L2: 99606 | M2: 73940 | N2: 57126 | O2: 52441 | P2: 78781 | Q2: 47665 | R2: 42947 | S2: 86818 | T2: 119147 | U2: 83344
A3: South | B3: South England | C3: R. Okafor | D3: 1200000 | E3: 14.1 | F3: Yes | I3: South England | J3: 81860 | K3: 88927 | L3: 110461 | M3: 75264 | N3: 77756 | O3: 107898 | P3: 71355 | Q3: 82611 | R3: 40690 | S3: 67299 | T3: 55402 | U3: 77989
A4: East | B4: East England | C4: L. Bennett | D4: 700000 | E4: 6.3 | F4: Yes | I4: East England | J4: 64321 | K4: 107670 | L4: 55493 | M4: 117444 | N4: 102393 | O4: 73807 | P4: 49070 | Q4: 88068 | R4: 87426 | S4: 103209 | T4: 102964 | U4: 88135
A5: West | B5: West England | C5: S. Hughes | D5: 750000 | E5: 5.8 | F5: Yes | I5: West England | J5: 84202 | K5: 113395 | L5: 64807 | M5: 100928 | N5: 104554 | O5: 117077 | P5: 41371 | Q5: 99345 | R5: 42211 | S5: 80780 | T5: 108269 | U5: 76733
A6: Midlands | B6: Midlands | C6: M. Patel | D6: 900000 | E6: 10.7 | F6: Yes | I6: Midlands | J6: 49755 | K6: 112160 | L6: 48904 | M6: 109382 | N6: 80360 | O6: 114417 | P6: 60225 | Q6: 80910 | R6: 54235 | S6: 109663 | T6: 57343 | U6: 91742
A7: Scotland | B7: Scotland | C7: D. Morgan | D7: 600000 | E7: 5.5 | F7: Yes | I7: Scotland | J7: 104226 | K7: 101733 | L7: 66765 | M7: 116820 | N7: 111822 | O7: 83118 | P7: 104753 | Q7: 44694 | R7: 64548 | S7: 76103 | T7: 109413 | U7: 84471
A8: Wales | B8: Wales | C8: A. Singh | D8: 400000 | E8: 3.2 | F8: Yes | I8: Wales | J8: 44679 | K8: 80613 | L8: 105951 | M8: 49655 | N8: 53469 | O8: 98732 | P8: 98756 | Q8: 71627 | R8: 88343 | S8: 84666 | T8: 83147 | U8: 67294
A9: NI | B9: Northern Ireland | C9: T. Williams | D9: 250000 | E9: 1.9 | F9: Yes | I9: Northern Ireland | J9: 99629 | K9: 49813 | L9: 91735 | M9: 62153 | N9: 92752 | O9: 75343 | P9: 115522 | Q9: 112172 | R9: 116512 | S9: 108512 | T9: 42454 | U9: 80174

Sheet REF_Products
A1: ProductID | B1: Product Name | C1: Category | D1: Cost Price | E1: Supplier | F1: Min Order Qty | G1: Lead Days
A2: PRD001 | B2: Laptop Pro 15 | C2: Electronics | D2: 112.58 | E2: GlobalGoods Co | F2: 39 | G2: 15
A3: PRD002 | B3: Wireless Mouse | C3: Electronics | D3: 398.82 | E3: GlobalGoods Co | F3: 10 | G3: 3
A4: PRD003 | B4: USB-C Hub | C4: Electronics | D4: 272.09 | E4: DirectBuy | F4: 12 | G4: 2
A5: PRD004 | B5: Mechanical Keyboard | C5: Electronics | D5: 174.44 | E5: FastMart | F5: 6 | G5: 9
A6: PRD005 | B6: Monitor 27in | C6: Electronics | D6: 500.77 | E6: TechSource Ltd | F6: 43 | G6: 13
A7: PRD006 | B7: Webcam HD | C7: Electronics | D7: 311.94 | E7: GlobalGoods Co | F7: 41 | G7: 15
A8: PRD007 | B8: Office Chair | C8: Furniture | D8: 373.96 | E8: FastMart | F8: 19 | G8: 17
A9: PRD008 | B9: Standing Desk | C9: Furniture | D9: 146.96 | E9: QuickShip UK | F9: 32 | G9: 6
A10: PRD009 | B10: Desk Lamp | C10: Furniture | D10: 127.85 | E10: QuickShip UK | F10: 14 | G10: 8
A11: PRD010 | B11: Filing Cabinet | C11: Furniture | D11: 392.01 | E11: FastMart | F11: 40 | G11: 17
A12: PRD011 | B12: Whiteboard A1 | C12: Stationery | D12: 74.77 | E12: DirectBuy | F12: 11 | G12: 13
A13: PRD012 | B13: Notebook Pack | C13: Stationery | D13: 409.37 | E13: TechSource Ltd | F13: 33 | G13: 20
... A41: PRD040 | B41: Trainers Size 9 | C41: Clothing | D41: 223.82 | E41: QuickShip UK | F41: 50 | G41: 8

Sheet REF_Employees
A1: EmployeeID | B1: Department | C1: Job Grade | D1: Manager | E1: Office Location
A2: EMP001 | B2: Finance | C2: Director | D2: J. Carter | E2: Birmingham
A3: EMP002 | B3: Customer Service | C3: Senior | D3: T. Williams | E3: Belfast
A4: EMP003 | B4: Logistics | C4: Senior | D4: R. Okafor | E4: Birmingham
A5: EMP004 | B5: Marketing | C5: Senior | D5: T. Williams | E5: Edinburgh
A6: EMP005 | B6: IT | C6: Manager | D6: S. Hughes | E6: Belfast
A7: EMP006 | B7: Sales | C7: Junior | D7: S. Hughes | E7: Manchester
A8: EMP007 | B8: Operations | C8: Junior | D8: L. Bennett | E8: Cardiff
A9: EMP008 | B9: HR | C9: Senior | D9: A. Singh | E9: Cardiff
A10: EMP009 | B10: IT | C10: Lead | D10: A. Singh | E10: Edinburgh
A11: EMP010 | B11: Operations | C11: Senior | D11: A. Singh | E11: Edinburgh
A12: EMP011 | B12: Operations | C12: Senior | D12: A. Singh | E12: Cardiff
... A84: EMP083 | B84: Finance | C84: Manager | D84: J. Carter | E84: Manchester

Sheet REF_PriceBands
A1: Min Price | B1: Max Price | C1: Band | D1: Discount % | E1: Free Shipping
A2: 0 | B2: 24.99 | C2: Budget | D2: 0 | E2: No
A3: 25 | B3: 49.99 | C3: Standard | D3: 5 | E3: No
A4: 50 | B4: 99.99 | C4: Mid-Range | D4: 8 | E4: Yes
A5: 100 | B5: 199.99 | C5: Premium | D5: 12 | E5: Yes
A6: 200 | B6: 499.99 | C6: High-End | D6: 15 | E6: Yes
A7: 500 | B7: 9999 | C7: Luxury | D7: 20 | E7: Yes

Sheet PivotTables
A2: Revenue Trend | G2: Revenue Trend
A3: Order Date Year | B3: Order Date Month | C3: Sum of Total Revenue Per Purchase
A4: 2023 | B4: January | C4: 5984.4
B5: February | C5: 2304.32
B6: March | C6: 3284.22
B7: April | C7: 7853.21
B8: May | C8: 6896.56
B9: June | C9: 5447.48
B10: July | C10: 5444.48
B11: August | C11: 5059.62
B12: September | C12: 3933.74
B13: October | C13: 6405.34
B14: November | C14: 8004.72
B15: December | C15: 5664.79
A16: 2023 Total | C16: 66282.88
A17: 2024 | B17: January | C17: 6940.93
B18: February | C18: 11189.93
B19: March | C19: 4903.81
B20: April | C20: 5916.21 | K20: Performance Score Per Annual Salary
B21: May | C21: 9028.62
B22: June | C22: 9381.38
A23: 2024 Total | C23: 47360.88
A24: Grand Total | C24: 113643.76
A27: Orders Per Category | D27: Orders Per Category
A28: Category | B28: Count of CustomerID
A29: Books | B29: 25
A30: Clothing | B30: 15
A31: Electronics | B31: 25
A32: Furniture | B32: 10
A33: Health | B33: 19
A34: Kitchen | B34: 20
A35: Sportswear | B35: 17
A36: Stationery | B36: 19
A37: Grand Total | B37: 150
A40: Revenue Per Category | D40: Revenue Per Category
A41: Category | B41: Sum of Total Revenue Per Purchase
A42: Books | B42: 17417.32
A43: Clothing | B43: 9685.41
A44: Electronics | B44: 11844.41
A45: Furniture | B45: 8592.59
A46: Health | B46: 11163.56
A47: Kitchen | B47: 18441.09
A48: Sportswear | B48: 13481.54
A49: Stationery | B49: 23017.84
A50: Grand Total | B50: 113643.76
A53: Return By Reason | D53: Return By Reason
A54: Reason | B54: Count of ReturnID
A55: Changed mind | B55: 4
A56: Damaged | B56: 7
A57: Defective | B57: 9
A58: Duplicate order | B58: 3
A59: Not as described | B59: 6
A60: Too large | B60: 5
A61: Too small | B61: 4
A62: Unknown | B62: 5
A63: Wrong item | B63: 7
A64: Grand Total | B64: 50
A67: Performance Score Per Department | J67: Performance Score Per Department
A68: Count of Performance Score 2 | B68: Performance Score 2
A69: Department | B69: Excellent | C69: Good | D69: Marginal | E69: Poor | F69: Grand Total
A70: Customer Service | C70: 4 | D70: 5 | E70: 6 | F70: 15
A71: Finance | B71: 2 | D71: 3 | E71: 5 | F71: 10
A72: HR | C72: 1 | E72: 3 | F72: 4
A73: IT | B73: 2 | C73: 1 | D73: 2 | E73: 4 | F73: 9
A74: Logistics | B74: 3 | C74: 4 | D74: 2 | E74: 3 | F74: 12
A75: Marketing | C75: 1 | D75: 3 | E75: 1 | F75: 5
A76: N/A | C76: 1 | D76: 1 | E76: 1 | F76: 3
A77: Operations | B77: 3 | C77: 3 | D77: 6 | E77: 1 | F77: 13
A78: Sales | B78: 4 | C78: 3 | D78: 3 | E78: 2 | F78: 12
A79: Grand Total | B79: 14 | C79: 18 | D79: 25 | E79: 26 | F79: 83
A82: Average Annual Salary Per Department | D82: Average Annual Salary Per Department
A83: Department | B83: Average of Annual Salary
A84: Customer Service | B84: 57031.6
A85: Finance | B85: 52001.7
A86: HR | B86: 54942.5
A87: IT | B87: 50605.222
A88: Logistics | B88: 50322.167
A89: Marketing | B89: 48538.2
A90: N/A | B90: 58648.667
A91: Operations | B91: 53584.5
A92: Sales | B92: 52157.917
A93: Grand Total | B93: 52952.683

Sheet Dashboard
A1: NovaMart Sales and Employees Dashboard
B11: Total Orders | P11: Total Revenue
B14: =COUNT(Orders_Clean!D2:D154) -> 150 | P14: =SUM(Orders_Clean!N2:N154) -> 113643.76
A17: Revenue Trend | K17: Revenue Per Category | U17: Orders Per Category
B36: Total Employees | P36: Lowest Average Performance Grade
B39: =COUNTA(Employees_Clean!A2:A81) -> 80 | P39: =_xlfn.XLOOKUP(MIN(Employees_Clean!F2:F81),Employees_Clean!F2:F81,Employees_Clean!C2:C81) -> IT
A42: Average Annual Salary Per Department | K42: Performance Score Per Annual Salary | U42: Performance Score Per Department
